setup.cfg
setup.py
btlejuice/__init__.py
btlejuice/exceptions.py
btlejuice/interface.py
btlejuice/utils.py
btlejuice.egg-info/PKG-INFO
btlejuice.egg-info/SOURCES.txt
btlejuice.egg-info/dependency_links.txt
btlejuice.egg-info/requires.txt
btlejuice.egg-info/top_level.txt
btlejuice/socketIO_client/__init__.py
btlejuice/socketIO_client/exceptions.py
btlejuice/socketIO_client/heartbeats.py
btlejuice/socketIO_client/logs.py
btlejuice/socketIO_client/namespaces.py
btlejuice/socketIO_client/parsers.py
btlejuice/socketIO_client/symmetries.py
btlejuice/socketIO_client/transports.py