Metadata-Version: 1.0
Name: btlejuice
Version: 1.1
Summary: BtleJuice MitM framework Python bindings
Home-page: https://github.com/DigitalSecurity/btlejuice-python-bindings
Author: Damien Cauquil
Author-email: damien.cauquil@digitalsecurity.fr
License: MIT
Platform: UNKNOWN
